LICENCE.txt
MANIFEST.in
README.txt
setup.py
pythondhanya/__init__.py
pythondhanya.egg-info/PKG-INFO
pythondhanya.egg-info/SOURCES.txt
pythondhanya.egg-info/dependency_links.txt
pythondhanya.egg-info/top_level.txt