Metadata-Version: 2.1
Name: pythondhanya
Version: 0.0.1
Summary: this is a trial package used for calculation.
Home-page: UNKNOWN
Author: Dhanya Shree
Author-email: dhanya02.ps@gmail.com
License: MIT
Platform: UNKNOWN
License-File: LICENCE.txt
